{
  "article": {
    "id": 82529,
    "link": "https://clients3.weblink.com.au/Clients/JuniorMining/headline.aspx?id=61244481",
    "title": "Exploration Agreement with Option to Purchase North Fork",
    "description": "AA Megado ASX ANNOUNCEMENT 19 December 2024 MINERALS Megado Executes Exploration Agreement with Option to Purchase with lluka Subsidiary for North Fork Project HIGHLIGHTS «Exploration Agreement with Option to Purchase executed with PURE Exploration (USA) LLC, a wholly owned subsidiary of lluka Resources Limited for the North Fork Rare Earth Project, Idaho, USA * Three tranche transaction agreed = First Tranche — lluka to pay A$500k and reimburse Megado up to US$110k for claim maintenance fees incurred in 2024 for an exclusive two-year right to explore the property = Second Tranche — During the two-year period, lluka may elect to purchase 100% of the Project for AS$1m - Third Tranche — Iluka to pay Megado A$2m within 30 days of lluka achieving US$10m in revenues from the property. Iluka may convert this obligation to a 2% gross revenue royalty Megado Minerals Limited (ASX: MEG) (Megado or the Company) is pleased to advise it has executed an Exploration Agreement with Option to Purchase with PURE Exploration (USA) LLC, a wholly owned subsidiary of Iluka Resources Limited (ASX: ILU) (Iluka) for the North Fork Rare Earth Project located in Idaho, USA (North Fork Project). The proposed transaction under the agreement is split into three tranches: 1. First Tranche: Iluka to pay the Company A$500k and reimburse the Company up to US$110k for claim maintenance fees incurred in 2024, for an exclusive two-year right to explore the property with all exploration costs and claim maintenance fees on lluka’s account during this period; 2. Second Tranche: At any time during the two-year exclusive exploration period, Iluka may elect to purchase 100% of the Project by paying Megado A$1m, minus any amounts that may be due to lluka by Megado or a Megado subsidiary. The two-year period may be extended in certain circumstances; and 3. Third Tranche: Iluka to pay Megado A$2m within 30 days of lluka receiving US$10m in revenues from the first sale of product from the North Fork Project after commencement of commercial production. Iluka may convert this obligation to a 2% gross revenue royalty. ASX has confirmed to Megado that ASX Listing Rule 11.2 does not apply to the proposed transaction and, on that basis, Megado does not require shareholder approval of the proposed transaction. -ENDS-  Authorised for release by: The Board of Megado Minerals Limited. For more information: Anthony Hall Elvis Jurcevic Chairman Investor Relations +61 417 466 039 +61 408 268 271 ahall@megadominerals.com ej@irxadvisors.com AA Megado MINERALS ‘www.megadominerals.com",
    "search_terms": "North Fork,Megado Minerals Ltd,MEG",
    "master_gid": 9385,
    "date": "2024-12-18T21:14:03.000Z",
    "tags": "USA|Idaho|||Project Acquisition",
    "image_id": null,
    "hidden": false,
    "company_id": 4177,
    "provider": "ASX",
    "excerpt": "Megado Minerals Ltd (ASX:MEG)",
    "is_regulatory": false,
    "refined_tags": null,
    "ftp_filename": null,
    "company_name": "Megado Minerals Ltd",
    "exchange": "ASX",
    "root_ticker": "MEG",
    "project_name": "North Fork",
    "gid": 9385,
    "location": "Idaho, United States",
    "plan_id": null,
    "description_text": "AA Megado ASX ANNOUNCEMENT 19 December 2024 MINERALS Megado Executes Exploration Agreement with Option to Purchase with lluka Subsidiary for North Fork Project HIGHLIGHTS «Exploration Agreement with Option to Purchase executed with PURE Exploration (USA) LLC, a wholly owned subsidiary of lluka Resources Limited for the North Fork Rare Earth Project, Idaho, USA * Three tranche transaction agreed = First Tranche — lluka to pay A$500k and reimburse Megado up to US$110k for claim maintenance fees incurred in 2024 for an exclusive two-year right to explore the property = Second Tranche — During the two-year period, lluka may elect to purchase 100% of the Project for AS$1m - Third Tranche — Iluka to pay Megado A$2m within 30 days of lluka achieving US$10m in revenues from the property. Iluka may convert this obligation to a 2% gross revenue royalty Megado Minerals Limited (ASX: MEG) (Megado or the Company) is pleased to advise it has executed an Exploration Agreement with Option to Purchase with PURE Exploration (USA) LLC, a wholly owned subsidiary of Iluka Resources Limited (ASX: ILU) (Iluka) for the North Fork Rare Earth Project located in Idaho, USA (North Fork Project). The proposed transaction under the agreement is split into three tranches: 1. First Tranche: Iluka to pay the Company A$500k and reimburse the Company up to US$110k for claim maintenance fees incurred in 2024, for an exclusive two-year right to explore the property with all exploration costs and claim maintenance fees on lluka’s account during this period; 2. Second Tranche: At any time during the two-year exclusive exploration period, Iluka may elect to purchase 100% of the Project by paying Megado A$1m, minus any amounts that may be due to lluka by Megado or a Megado subsidiary. The two-year period may be extended in certain circumstances; and 3. Third Tranche: Iluka to pay Megado A$2m within 30 days of lluka receiving US$10m in revenues from the first sale of product from the North Fork Project after commencement of commercial production. Iluka may convert this obligation to a 2% gross revenue royalty. ASX has confirmed to Megado that ASX Listing Rule 11.2 does not apply to the proposed transaction and, on that basis, Megado does not require shareholder approval of the proposed transaction. -ENDS-  Authorised for release by: The Board of Megado Minerals Limited. For more information: Anthony Hall Elvis Jurcevic Chairman Investor Relations +61 417 466 039 +61 408 268 271 ahall@megadominerals.com ej@irxadvisors.com AA Megado MINERALS ‘www.megadominerals.com",
    "primary_commodity": "REE"
  },
  "articleProject": {
    "gid": 9385,
    "project_name": "North Fork",
    "location": "Idaho, United States"
  },
  "articleExchange": "ASX",
  "articleCompanyId": 4177,
  "articleTicker": "MEG",
  "articleCompanyName": "Megado Minerals Ltd",
  "allOtherCompanyProjects": [
    {
      "company_id": 4177,
      "gid": 9385,
      "project_name": "North Fork",
      "location": "Idaho, United States"
    },
    {
      "company_id": 4177,
      "gid": 8928,
      "project_name": "Iberian Copper Project",
      "location": null
    }
  ],
  "allOtherCompanyNews": [
    {
      "id": 108030,
      "company_id": 4177,
      "title": "Investor Presentation - June 2025",
      "link": "https://clients3.weblink.com.au/Clients/JuniorMining/headline.aspx?id=61268584",
      "date": "2025-06-15T21:21:39.000Z",
      "hidden": false
    },
    {
      "id": -204489,
      "company_id": 4177,
      "title": "Section 708A Notice - Share Issue",
      "link": "https://clients3.weblink.com.au/Clients/JuniorMining/headline.aspx?id=61268551",
      "date": "2025-06-13T06:07:29.000Z",
      "hidden": false
    },
    {
      "id": -204488,
      "company_id": 4177,
      "title": "Change of Director's Interest Notice x 3",
      "link": "https://clients3.weblink.com.au/Clients/JuniorMining/headline.aspx?id=61268549",
      "date": "2025-06-13T06:00:04.000Z",
      "hidden": false
    },
    {
      "id": -204482,
      "company_id": 4177,
      "title": "Notification regarding unquoted securities - MEG",
      "link": "https://clients3.weblink.com.au/Clients/JuniorMining/headline.aspx?id=61268533",
      "date": "2025-06-13T05:40:49.000Z",
      "hidden": false
    },
    {
      "id": 107895,
      "company_id": 4177,
      "title": "MEG Completes Acquisition of Major European Copper Project",
      "link": "https://clients3.weblink.com.au/Clients/JuniorMining/headline.aspx?id=61268400",
      "date": "2025-06-12T21:24:06.000Z",
      "hidden": false
    },
    {
      "id": -202501,
      "company_id": 4177,
      "title": "Results of Annual General Meeting",
      "link": "https://clients3.weblink.com.au/Clients/JuniorMining/headline.aspx?id=61266546",
      "date": "2025-05-29T04:46:37.000Z",
      "hidden": false
    },
    {
      "id": 105964,
      "company_id": 4177,
      "title": "Investor Presentation - 28 May 2025",
      "link": "https://clients3.weblink.com.au/Clients/JuniorMining/headline.aspx?id=61266227",
      "date": "2025-05-27T21:15:11.000Z",
      "hidden": false
    },
    {
      "id": -199246,
      "company_id": 4177,
      "title": "Change of Director's Interest Notice",
      "link": "https://clients3.weblink.com.au/Clients/JuniorMining/headline.aspx?id=61263465",
      "date": "2025-05-05T23:44:02.000Z",
      "hidden": false
    },
    {
      "id": 101864,
      "company_id": 4177,
      "title": "Quarterly Activities Report & Appendix 5B",
      "link": "https://clients3.weblink.com.au/Clients/JuniorMining/headline.aspx?id=61261641",
      "date": "2025-04-27T23:34:10.000Z",
      "hidden": false
    },
    {
      "id": -196639,
      "company_id": 4177,
      "title": "Notice of Annual General Meeting/Proxy Form",
      "link": "https://clients3.weblink.com.au/Clients/JuniorMining/headline.aspx?id=61261640",
      "date": "2025-04-27T23:25:35.000Z",
      "hidden": false
    }
  ]
}
